octalearn/__init__.py
octalearn/path_management.py
octalearn/util.py
octalearn-0.3.0.dist-info/WHEEL
octalearn-0.3.0.dist-info/METADATA
octalearn-0.3.0.dist-info/RECORD
