Metadata-Version: 2.1
Name: octalearn
Version: 0.3.0
Summary: A sample project for showing basic python package management
License: MPL-2.0
Author: Aldrin
Author-email: akmontan@ucsc.edu
Requires-Python: >=3.9,<4.0
Classifier: License :: OSI Approved
Classifier: Programming Language :: Python :: 3
Classifier: Programming Language :: Python :: 3.9
